LICENSE.txt
MANIFEST.in
README.md
setup.py
test.py
../../src/array.c
../../src/base64.c
../../src/buffer.c
../../src/cdb.c
../../src/cdb_make.c
../../src/dict.c
../../src/diff.c
../../src/disk.c
../../src/fmt.c
../../src/ht_pp.c
../../src/ht_pu.c
../../src/ht_up.c
../../src/ht_uu.c
../../src/journal.c
../../src/json.c
../../src/lock.c
../../src/ls.c
../../src/main.c
../../src/match.c
../../src/ns.c
../../src/num.c
../../src/query.c
../../src/sdb.c
../../src/sdbht.c
../../src/set.c
../../src/text.c
../../src/util.c
nsdb/lib.c
r2sdb/__init__.py
r2sdb.egg-info/PKG-INFO
r2sdb.egg-info/SOURCES.txt
r2sdb.egg-info/dependency_links.txt
r2sdb.egg-info/top_level.txt
sdbsrc/array.c
sdbsrc/base64.c
sdbsrc/buffer.c
sdbsrc/buffer.h
sdbsrc/cdb.c
sdbsrc/cdb.h
sdbsrc/cdb_make.c
sdbsrc/cdb_make.h
sdbsrc/config.h
sdbsrc/dict.c
sdbsrc/dict.h
sdbsrc/diff.c
sdbsrc/disk.c
sdbsrc/fmt.c
sdbsrc/ht.inc
sdbsrc/ht_inc.h
sdbsrc/ht_pp.c
sdbsrc/ht_pp.h
sdbsrc/ht_pu.c
sdbsrc/ht_pu.h
sdbsrc/ht_up.c
sdbsrc/ht_up.h
sdbsrc/ht_uu.c
sdbsrc/ht_uu.h
sdbsrc/journal.c
sdbsrc/json.c
sdbsrc/lock.c
sdbsrc/ls.c
sdbsrc/ls.h
sdbsrc/main.c
sdbsrc/match.c
sdbsrc/ns.c
sdbsrc/num.c
sdbsrc/query.c
sdbsrc/sdb.c
sdbsrc/sdb.h
sdbsrc/sdb_version.h
sdbsrc/sdbht.c
sdbsrc/sdbht.h
sdbsrc/set.c
sdbsrc/set.h
sdbsrc/text.c
sdbsrc/types.h
sdbsrc/util.c
sdbsrc/json/api.c
sdbsrc/json/indent.c
sdbsrc/json/js0n.c
sdbsrc/json/main.c
sdbsrc/json/path.c
sdbsrc/json/rangstr.c
sdbsrc/json/rangstr.h
sdbsrc/json/test.c